odoo/addons/account_statement_import_camt54/README.rst
odoo/addons/account_statement_import_camt54/__init__.py
odoo/addons/account_statement_import_camt54/__manifest__.py
odoo/addons/account_statement_import_camt54/i18n/account_statement_import_camt54.pot
odoo/addons/account_statement_import_camt54/i18n/es.po
odoo/addons/account_statement_import_camt54/i18n/it.po
odoo/addons/account_statement_import_camt54/i18n/nl.po
odoo/addons/account_statement_import_camt54/models/__init__.py
odoo/addons/account_statement_import_camt54/models/account_journal.py
odoo/addons/account_statement_import_camt54/models/account_statement_import.py
odoo/addons/account_statement_import_camt54/models/parser.py
odoo/addons/account_statement_import_camt54/readme/CONTRIBUTORS.md
odoo/addons/account_statement_import_camt54/readme/CREDITS.md
odoo/addons/account_statement_import_camt54/readme/DESCRIPTION.md
odoo/addons/account_statement_import_camt54/static/description/icon.png
odoo/addons/account_statement_import_camt54/static/description/index.html
odoo/addons/account_statement_import_camt54/tests/__init__.py
odoo/addons/account_statement_import_camt54/tests/test_get_partner_ref.py
odoo/addons/account_statement_import_camt54/tests/test_statement.py
odoo/addons/account_statement_import_camt54/views/account_journal_view.xml
odoo_addon_account_statement_import_camt54-18.0.1.0.0.2.dist-info/METADATA
odoo_addon_account_statement_import_camt54-18.0.1.0.0.2.dist-info/WHEEL
odoo_addon_account_statement_import_camt54-18.0.1.0.0.2.dist-info/top_level.txt
odoo_addon_account_statement_import_camt54-18.0.1.0.0.2.dist-info/RECORD
